tinuipicker/__init__.py
tinuipicker/datepicker.py
tinuipicker/timepicker.py
tinuipicker-1.1.0.dist-info/licenses/LICENSE
tinuipicker-1.1.0.dist-info/METADATA
tinuipicker-1.1.0.dist-info/WHEEL
tinuipicker-1.1.0.dist-info/top_level.txt
tinuipicker-1.1.0.dist-info/RECORD
