Metadata-Version: 2.4
Name: tinuipicker
Version: 1.1.0
Summary: tinui扩展数据滚动选择器
Author-email: Smart-Space <smart-space@qq.com>
License-Expression: Apache-2.0
Project-URL: Repository, https://github.com/Smart-Space/TinUIPicker
Classifier: Programming Language :: Python :: 3
Classifier: Operating System :: OS Independent
Requires-Python: >=3.8
License-File: LICENSE
Requires-Dist: tinui
Dynamic: license-file
